weeb/__init__.py
weeb/client.py
weeb/errors.py
weeb.py-1.1.0.dist-info/DESCRIPTION.rst
weeb.py-1.1.0.dist-info/METADATA
weeb.py-1.1.0.dist-info/RECORD
weeb.py-1.1.0.dist-info/WHEEL
weeb.py-1.1.0.dist-info/metadata.json
weeb.py-1.1.0.dist-info/top_level.txt
