Metadata-Version: 2.0
Name: weeb.py
Version: 1.1.0
Summary: An API wrapper for weeb.sh
Home-page: https://github.com/Desiiii/weeb.py
Author: Desiiii
Author-email: godavaru@gmail.com
License: UNKNOWN
Platform: UNKNOWN
Classifier: Development Status :: 4 - Beta
Classifier: Intended Audience :: Developers
Classifier: License :: OSI Approved :: MIT License
Classifier: Programming Language :: Python :: 3 :: Only
Classifier: Programming Language :: Python :: 3.6
Requires-Python: >=3.4, <4
